LICENSE
MANIFEST.in
README.rst
setup.py
DynIP.egg-info/PKG-INFO
DynIP.egg-info/SOURCES.txt
DynIP.egg-info/dependency_links.txt
DynIP.egg-info/entry_points.txt
DynIP.egg-info/not-zip-safe
DynIP.egg-info/requires.txt
DynIP.egg-info/top_level.txt
dynip/__init__.py
dynip/client.py
dynip/return_codes.py
dynip/server.py
dynip/init/__init__.py
dynip/init/console.py