Metadata-Version: 1.0
Name: DynIP
Version: 0.1e
Summary: A painfully simple UDP Client/Server for tracking the IP addresses of your devices.
Home-page: http://www.rkrishardy.com
Author: Kris Hardy
Author-email: kris@rkrishardy.com
License: BSD
Keywords: udp ip tracking
Platform: UNKNOWN
Classifier: Topic :: Utilities
Classifier: Topic :: Internet
Classifier: Environment :: No Input/Output (Daemon)
Classifier: Development Status :: 4 - Beta
Classifier: Intended Audience :: System Administrators
Classifier: License :: OSI Approved :: BSD License
Classifier: Natural Language :: English
Classifier: Operating System :: OS Independent
Classifier: Programming Language :: Python
